odoo/addons/delivery_easypost_oca/README.rst
odoo/addons/delivery_easypost_oca/__init__.py
odoo/addons/delivery_easypost_oca/__manifest__.py
odoo/addons/delivery_easypost_oca/i18n/delivery_easypost_oca.pot
odoo/addons/delivery_easypost_oca/i18n/it.po
odoo/addons/delivery_easypost_oca/models/__init__.py
odoo/addons/delivery_easypost_oca/models/delivery_carrier.py
odoo/addons/delivery_easypost_oca/models/easypost_request.py
odoo/addons/delivery_easypost_oca/models/ir_logging.py
odoo/addons/delivery_easypost_oca/models/sale_order.py
odoo/addons/delivery_easypost_oca/models/stock_package_type.py
odoo/addons/delivery_easypost_oca/models/stock_picking.py
odoo/addons/delivery_easypost_oca/readme/CONFIGURE.md
odoo/addons/delivery_easypost_oca/readme/CONTRIBUTORS.md
odoo/addons/delivery_easypost_oca/readme/DESCRIPTION.md
odoo/addons/delivery_easypost_oca/readme/ROADMAP.md
odoo/addons/delivery_easypost_oca/readme/USAGE.md
odoo/addons/delivery_easypost_oca/static/description/icon.png
odoo/addons/delivery_easypost_oca/static/description/index.html
odoo/addons/delivery_easypost_oca/tests/__init__.py
odoo/addons/delivery_easypost_oca/tests/common.py
odoo/addons/delivery_easypost_oca/tests/mock_easypost.py
odoo/addons/delivery_easypost_oca/tests/test_delivery_carrier.py
odoo/addons/delivery_easypost_oca/tests/test_easypost_request.py
odoo/addons/delivery_easypost_oca/utils/pdf.py
odoo/addons/delivery_easypost_oca/utils/zpl.py
odoo/addons/delivery_easypost_oca/views/delivery_carrier_views.xml
odoo/addons/delivery_easypost_oca/views/stock_package_type.xml
odoo/addons/delivery_easypost_oca/wizard/__init__.py
odoo/addons/delivery_easypost_oca/wizard/choose_delivery_carrier.py
odoo_addon_delivery_easypost_oca-18.0.1.0.0.3.dist-info/METADATA
odoo_addon_delivery_easypost_oca-18.0.1.0.0.3.dist-info/WHEEL
odoo_addon_delivery_easypost_oca-18.0.1.0.0.3.dist-info/top_level.txt
odoo_addon_delivery_easypost_oca-18.0.1.0.0.3.dist-info/RECORD
