Metadata-Version: 2.1
Name: odoo-addon-delivery_easypost_oca
Version: 18.0.1.0.0.3
Requires-Python: >=3.10
Requires-Dist: easypost==7.15.0
Requires-Dist: odoo==18.0.*
Summary: OCA Delivery Easypost
Home-page: https://github.com/OCA/delivery-carrier
License: AGPL-3
Author: Binhex, Odoo Community Association (OCA)
Author-email: support@odoo-community.org
Classifier: Programming Language :: Python
Classifier: Framework :: Odoo
Classifier: Framework :: Odoo :: 18.0
Classifier: License :: OSI Approved :: GNU Affero General Public License v3
